[
  {
    "model": "dosuke.config",
    "fields":{
      "key": "session_start",
      "value": "14",
      "memo": ""
    }
  },
  {
    "model": "dosuke.config",
    "fields":{
      "key": "session_end",
      "value": "20",
      "memo": ""
    }
  },
  {
    "model": "dosuke.config",
    "fields":{
      "key": "room_start",
      "value": "0",
      "memo": ""
    }
  },
  {
    "model": "dosuke.config",
    "fields":{
      "key": "room_end",
      "value": "27",
      "memo": ""
    }
  }
]